pymhf/__init__.py
pymhf/_preinject.py
pymhf/injected.py
pymhf/log_terminal.py
pymhf/main.py
pymhf/core/__init__.py
pymhf/core/_internal.py
pymhf/core/_types.py
pymhf/core/caching.py
pymhf/core/calling.py
pymhf/core/common.py
pymhf/core/errors.py
pymhf/core/functions.py
pymhf/core/hashing.py
pymhf/core/hooking.py
pymhf/core/importing.py
pymhf/core/log_handling.py
pymhf/core/memutils.py
pymhf/core/mod_loader.py
pymhf/core/module_data.py
pymhf/core/process.py
pymhf/core/protocols.py
pymhf/core/utils.py
pymhf/extensions/cpptypes.py
pymhf/extensions/ctypes.py
pymhf/gui/__init__.py
pymhf/gui/decorators.py
pymhf/gui/gui.py
pymhf/gui/hexview.py
pymhf/gui/protocols.py
pymhf/utils/config.py
pymhf/utils/iced.py
pymhf/utils/imports.py
pymhf/utils/parse_toml.py
pymhf/utils/partial_struct.py
pymhf/utils/winapi.py
pymhf-0.2.1.dist-info/licenses/LICENSE
pymhf-0.2.1.dist-info/METADATA
pymhf-0.2.1.dist-info/WHEEL
pymhf-0.2.1.dist-info/entry_points.txt
pymhf-0.2.1.dist-info/top_level.txt
pymhf-0.2.1.dist-info/RECORD
