Metadata-Version: 2.4
Name: pyMHF
Version: 0.2.1
Summary: python Modding and Hooking Framework
Author: monkeyman192
Maintainer: monkeyman192
License-Expression: MIT
Project-URL: homepage, https://github.com/monkeyman192/pyMHF
Project-URL: repository, https://github.com/monkeyman192/pyMHF.git
Project-URL: changelog, https://monkeyman192.github.io/pyMHF/docs/change_log.html
Project-URL: documentation, https://monkeyman192.github.io/pyMHF/index.html
Keywords: hooking,games,hacking,modding
Classifier: Development Status :: 2 - Pre-Alpha
Classifier: Environment :: Win32 (MS Windows)
Classifier: Operating System :: Microsoft
Classifier: Programming Language :: Python :: 3.9
Classifier: Programming Language :: Python :: 3.10
Classifier: Programming Language :: Python :: 3.11
Classifier: Programming Language :: Python :: 3.12
Classifier: Programming Language :: Python :: 3.13
Classifier: Programming Language :: Python :: 3 :: Only
Requires-Python: <4,>=3.9
License-File: LICENSE
Requires-Dist: cyminhook>=0.1.4
Requires-Dist: psutil~=5.9.5
Requires-Dist: pymem[speed]~=1.14.0
Requires-Dist: keyboard
Requires-Dist: pywin32
Requires-Dist: questionary
Requires-Dist: pywinctl
Requires-Dist: packaging
Requires-Dist: tomlkit
Requires-Dist: pefile
Requires-Dist: iced_x86
Requires-Dist: typing_extensions
Requires-Dist: pyrun-injected==0.2.0
Provides-Extra: gui
Requires-Dist: dearpygui; extra == "gui"
Dynamic: license-file
